<?xml version="1.0" encoding="UTF-8"?>
<hyperlinks>
<link><unistr>hlink_537ac8910f3b2</unistr><value>http://sydney.curtin.edu.au/</value></link><link><unistr>hlink_53c3cb8487e2f</unistr><value>http://sydney.curtin.edu.au</value></link><link><unistr>hlink_53c3cb8487f98</unistr><value>http://sydney.curtin.edu.au//chat.navitas.com/phplive.php?d=3&amp;onpage=livechatimagelink&amp;title=Live+Chat+Image+Link</value></link><link><unistr>hlink_53c3cb848abf0</unistr><value>http://sydney.curtin.edu.au/contact-us/</value></link><link><unistr>hlink_53c3cb848f662</unistr><value>http://curtin.edu.au/help/</value></link><link><unistr>hlink_53c3cb848f9d4</unistr><value>http://oasis.curtin.edu.au/</value></link><link><unistr>hlink_53c3cb8490534</unistr><value>http://find.curtin.edu.au/staff/index.cfm</value></link><link><unistr>hlink_53c3cb8491c72</unistr><value>http://sydney.curtin.edu.au/courses/</value></link><link><unistr>hlink_53c3cb8492c91</unistr><value>http://sydney.curtin.edu.au/future-students/</value></link><link><unistr>hlink_53c3cb84946c3</unistr><value>http://sydney.curtin.edu.au/current-students/</value></link><link><unistr>hlink_53c3cb8494a68</unistr><value>http://sydney.curtin.edu.au/courses/alternative-pathways/</value></link><link><unistr>hlink_53c3cb8496e4a</unistr><value>http://sydney.curtin.edu.au/current-students/library/</value></link><link><unistr>hlink_53c3cb8497065</unistr><value>http://sydney.curtin.edu.au/current-students/academic-calendar/</value></link><link><unistr>hlink_53c3cb84982cb</unistr><value>http://sydney.curtin.edu.au/courses/cross-institutional-enrolment/available-units/</value></link><link><unistr>hlink_53c3cb8498e11</unistr><value>http://sydney.curtin.edu.au/current-students/curtin-internship-program/</value></link><link><unistr>hlink_53c3cb8499b46</unistr><value>http://sydney.curtin.edu.au/future-students/agents-in-your-country/</value></link><link><unistr>hlink_53c3cb849b1b7</unistr><value>http://goo.gl/J3pV0E</value></link><link><unistr>hlink_53c3cb849d263</unistr><value>http://sydney.curtin.edu.au/current-students/upcoming-activities/</value></link><link><unistr>hlink_53c3cb849f102</unistr><value>https://docs.google.com/forms/d/1Ln7L-jruBHe9LP9U0z77tj-xUbpL5x8O7XkxQHI_tJE/viewform</value></link><link><unistr>hlink_53c3cb84a2c3a</unistr><value>https://docs.google.com/forms/d/1eYpFOp-A_DtTO_QkgDgxd383aoysPR46X81RWhAsz8s/viewform</value></link><link><unistr>hlink_53c3cb84a352f</unistr><value>https://docs.google.com/forms/d/16wgoFIKTTiCvViv-GUuFXOCdxwjm18SRTMhokBGVDbk/viewform</value></link><link><unistr>hlink_53c3cb84a6626</unistr><value>https://docs.google.com/forms/d/12e301IElULdcN96kFoe0ihh_2Pj61RgWZBCCM_aPXcE/viewform</value></link><link><unistr>hlink_53c3cb84a6b51</unistr><value>http://study.navitas.com/CUS-AUS-Website-MCOM-July-14.html</value></link><link><unistr>hlink_53c3cb84a7dd1</unistr><value>http://sydney.curtin.edu.au/future-students/how-to-apply/</value></link><link><unistr>hlink_53c3cb84a8715</unistr><value>http://sydney.curtin.edu.au/files/2014/04/Curtin-Internship-Program-Schedule-March-2014.pdf</value></link><link><unistr>hlink_53c3cb84a9d70</unistr><value>http://sydney.curtin.edu.au/2014-curtin-college-scholarships/</value></link><link><unistr>hlink_53c3cb84aaa51</unistr><value>http://sydney.curtin.edu.au/2014-scholarships/</value></link><link><unistr>hlink_53c3cb84abae1</unistr><value>http://sydney.curtin.edu.au/courses/undergraduate/</value></link><link><unistr>hlink_53c3cb84ac6c4</unistr><value>http://sydney.curtin.edu.au/courses/postgraduate/</value></link><link><unistr>hlink_53c3cb84add94</unistr><value>http://sydney.curtin.edu.au/graduation-speech-tracy-shi/</value></link><link><unistr>hlink_53c3cb84ae611</unistr><value>http://study.navitas.com/CUS-Website-CrossIn1402.html</value></link><link><unistr>hlink_53c3cb84b0134</unistr><value>http://sydney.curtin.edu.au/files/2013/01/CCS1982-Course-Flyer-English-A4P-4pp_WEB1.pdf</value></link><link><unistr>hlink_53c3cb84b1bde</unistr><value>https://twitter.com/curtinsydney</value></link><link><unistr>hlink_53c3cb84b1f6a</unistr><value>http://sydney.curtin.edu.au/contact-us/admission-enquiry-form/</value></link><link><unistr>hlink_53c3cb84b3cf4</unistr><value>http://sydney.curtin.edu.au/contact-us/comments-complaints-and-feedback/</value></link><link><unistr>hlink_53c3cb84b5129</unistr><value>http://www.curtin.edu.au/</value></link><link><unistr>hlink_53c3cb84b6e97</unistr><value>http://about.curtin.edu.au/our-locations.cfm</value></link><link><unistr>hlink_53c3cb84b8dbd</unistr><value>http://www.curtin.edu.my/</value></link><link><unistr>hlink_53c3cb84bad78</unistr><value>http://www.curtin.edu.sg/</value></link><link><unistr>hlink_53c3cb84be414</unistr><value>http://www.facebook.com/curtinsydney</value></link><link><unistr>hlink_53c3cb84c029c</unistr><value>http://www.youtube.com/curtinsydney</value></link><link><unistr>hlink_53c3cb84c31cc</unistr><value>http://www.flickr.com/photos/curtinuni/</value></link><link><unistr>hlink_53c3cb84c7562</unistr><value>http://e.weibo.com/curtinsydney</value></link><link><unistr>hlink_53c3cb84cb174</unistr><value>http://global.curtin.edu.au/legal/</value></link><link><unistr>hlink_53c3cb84cd433</unistr><value>http://sydney.curtin.edu.au/privacy/</value></link><link><unistr>hlink_53c3cb84d159e</unistr><value>http://www.curtin.edu.au/accessibility/</value></link><link><unistr>hlink_53c3cb84d5564</unistr><value>http://search.curtin.edu.au/s/search.html</value></link><link><unistr>hlink_53c3cbc5dd9f6</unistr><value>http://sydney.curtin.edu.au/files/2013/11/Scholarship-2014-banner-How-does-is-work.jpg</value></link><link><unistr>hlink_53c3cbc5ddc80</unistr><value>http://sydney.curtin.edu.au/files/2013/11/Scholarships-2014-website-pic-21.jpg</value></link><link><unistr>hlink_53c3cbe473494</unistr><value>http://study.navitas.com/index.php/leadCapture/save</value></link><link><unistr>hlink_542aa5ec89344</unistr><value>http://sydney.curtin.edu.au/current-students/upcoming-activities/hollywoods-jeff-gomez-transmedia-storytelling-masterclass/</value></link><link><unistr>hlink_542aa5ec89efc</unistr><value>http://sydney.curtin.edu.au/files/2014/08/Curtin-Internship-Program-Schedule-August-2014_v1.pdf</value></link><link><unistr>hlink_542aa5ec8be3d</unistr><value>http://sydney.curtin.edu.au/current-students/academic-workshops/</value></link><link><unistr>hlink_542aa5ec8c60d</unistr><value>http://sydney.curtin.edu.au/global-education-alliances-annual-agent-workshop-guangzhou-china/</value></link><link><unistr>hlink_542aa5ec8c9f5</unistr><value>http://study.navitas.com/study.sydney.curtin.edu.au-start1403.html</value></link></hyperlinks>
